deadline/__main__.py
deadline/_mcp/__init__.py
deadline/_mcp/registry.py
deadline/_mcp/server.py
deadline/_mcp/utils.py
deadline/_mcp/tools/__init__.py
deadline/_mcp/tools/job.py
deadline/client/__init__.py
deadline/client/_version.py
deadline/client/exceptions.py
deadline/client/py.typed
deadline/client/api/__init__.py
deadline/client/api/_get_storage_profile_for_queue.py
deadline/client/api/_job_attachment.py
deadline/client/api/_job_monitoring.py
deadline/client/api/_list_apis.py
deadline/client/api/_list_jobs_by_filter_expression.py
deadline/client/api/_loginout.py
deadline/client/api/_queue_credentials.py
deadline/client/api/_queue_parameters.py
deadline/client/api/_session.py
deadline/client/api/_submit_job_bundle.py
deadline/client/api/_telemetry.py
deadline/client/cli/__init__.py
deadline/client/cli/_common.py
deadline/client/cli/_deadline_web_url.py
deadline/client/cli/_incremental_download.py
deadline/client/cli/_main.py
deadline/client/cli/_main_for_docs.py
deadline/client/cli/_pid_file_lock.py
deadline/client/cli/_timestamp_formatter.py
deadline/client/cli/deadline_cli_main.py
deadline/client/cli/deadline_dev_gui_main.py
deadline/client/cli/_groups/__init__.py
deadline/client/cli/_groups/_sigint_handler.py
deadline/client/cli/_groups/attachment_group.py
deadline/client/cli/_groups/auth_group.py
deadline/client/cli/_groups/bundle_group.py
deadline/client/cli/_groups/click_logger.py
deadline/client/cli/_groups/config_group.py
deadline/client/cli/_groups/farm_group.py
deadline/client/cli/_groups/fleet_group.py
deadline/client/cli/_groups/handle_web_url_command.py
deadline/client/cli/_groups/job_group.py
deadline/client/cli/_groups/manifest_group.py
deadline/client/cli/_groups/mcp_server_command.py
deadline/client/cli/_groups/queue_group.py
deadline/client/cli/_groups/worker_group.py
deadline/client/config/__init__.py
deadline/client/config/config_file.py
deadline/client/dataclasses/__init__.py
deadline/client/dataclasses/submitter_info.py
deadline-0.54.0.dist-info/METADATA
deadline-0.54.0.dist-info/WHEEL
deadline-0.54.0.dist-info/entry_points.txt
deadline-0.54.0.dist-info/licenses/LICENSE
deadline-0.54.0.dist-info/licenses/NOTICE
deadline-0.54.0.dist-info/RECORD
