Metadata-Version: 2.4
Name: deadline
Version: 0.54.0
Summary: Multi-purpose library and command line tool that implements functionality to support applications using AWS Deadline Cloud.
Project-URL: Homepage, https://github.com/aws-deadline/deadline-cloud
Project-URL: Source, https://github.com/aws-deadline/deadline-cloud
Author: Amazon Web Services
License-Expression: Apache-2.0
License-File: LICENSE
License-File: NOTICE
Classifier: Development Status :: 5 - Production/Stable
Classifier: Intended Audience :: Developers
Classifier: Intended Audience :: End Users/Desktop
Classifier: License :: OSI Approved :: Apache Software License
Classifier: Operating System :: MacOS
Classifier: Operating System :: Microsoft :: Windows
Classifier: Operating System :: POSIX :: Linux
Classifier: Programming Language :: Python
Classifier: Programming Language :: Python :: 3 :: Only
Classifier: Programming Language :: Python :: 3.8
Classifier: Programming Language :: Python :: 3.9
Classifier: Programming Language :: Python :: 3.10
Classifier: Programming Language :: Python :: 3.11
Classifier: Programming Language :: Python :: 3.12
Classifier: Programming Language :: Python :: 3.13
Classifier: Topic :: Software Development :: Libraries
Requires-Python: <3.14,>=3.8
Requires-Dist: boto3>=1.36.8; python_version < '3.9'
Requires-Dist: boto3>=1.39.10; python_version >= '3.9'
Requires-Dist: click>=8.1.7
Requires-Dist: psutil>=7.0.0
Requires-Dist: pywin32<311,>=307; sys_platform == 'win32'
Requires-Dist: pyyaml>=6.0
Requires-Dist: qtpy==2.4.*
Requires-Dist: typing-extensions>=4.8
Requires-Dist: xxhash<3.7,>=3.4
Provides-Extra: gui
Requires-Dist: pyside6-essentials<6.11,>=6.6; extra == 'gui'
Provides-Extra: mcp
Requires-Dist: mcp>=1.13.0; extra == 'mcp'
